asyncio_subprocess_run.py
asyncio_subprocess_run-0.0.2.dist-info/LICENSE
asyncio_subprocess_run-0.0.2.dist-info/METADATA
asyncio_subprocess_run-0.0.2.dist-info/WHEEL
asyncio_subprocess_run-0.0.2.dist-info/top_level.txt
asyncio_subprocess_run-0.0.2.dist-info/RECORD
