Metadata-Version: 2.1
Name: asyncio-subprocess-run
Version: 0.0.2
Summary: http://github.com/vgavro/asyncio-subprocess-run
Home-page: http://github.com/vgavro/asyncio-subprocess-run
Author: Victor Gavro
Author-email: vgavro@gmail.com
License: MIT
Platform: UNKNOWN
Classifier: Programming Language :: Python :: 3
Classifier: Framework :: AsyncIO
